trespass/__init__.py
trespass-0.7.6.data/scripts/trespass
trespass-0.7.6.dist-info/METADATA
trespass-0.7.6.dist-info/WHEEL
trespass-0.7.6.dist-info/top_level.txt
trespass-0.7.6.dist-info/RECORD
