Metadata-Version: 2.1
Name: trespass
Version: 0.7.6
Summary: A secure password keeper
Home-page: https://github.com/gps1539/trespass
Author: Graham Smith
Author-email: gps1539@gmail.com
License: GPL3
Download-URL: https://github.com/gps1539/trespass/archive/0.7.6.tar.gz
Keywords: testing,logging,example
Platform: UNKNOWN
Requires-Dist: numpy
Requires-Dist: pygpgme
Requires-Dist: pyperclip
Requires-Dist: argparse
